chatter/__init__.py
chatter/analyzer.py
chatter/config.py
chatter/data.py
chatter/features.py
chatter/models.py
chatter/py.typed
chatter/trainer.py
chatter/utils.py
chatter_pkg-0.1.6.dist-info/licenses/LICENSE
chatter_pkg-0.1.6.dist-info/METADATA
chatter_pkg-0.1.6.dist-info/WHEEL
chatter_pkg-0.1.6.dist-info/top_level.txt
chatter_pkg-0.1.6.dist-info/RECORD
