Metadata-Version: 2.4
Name: chatter-pkg
Version: 0.1.6
Summary: A Python library for applying information theory and AI/ML models to animal communication.
Author-email: Mason Youngblood <masonyoungblood@gmail.com>
Requires-Python: >=3.13
License-File: LICENSE
Requires-Dist: audiocomplib>=0.2.0
Requires-Dist: biodenoising>=0.3.3
Requires-Dist: birdnetlib>=0.18.0
Requires-Dist: denmarf>=0.3.2
Requires-Dist: dtw-python>=1.7.2
Requires-Dist: h5py>=3.15.1
Requires-Dist: ipykernel>=7.1.0
Requires-Dist: ipympl>=0.9.8
Requires-Dist: ipython>=9.8.0
Requires-Dist: ipywidgets>=8.1.8
Requires-Dist: librosa>=0.9.2
Requires-Dist: matplotlib>=3.10.7
Requires-Dist: noisereduce>=3.0.3
Requires-Dist: numba>=0.62.1
Requires-Dist: numpy>=2.3.5
Requires-Dist: pacmap>=0.8.0
Requires-Dist: pandas>=2.3.3
Requires-Dist: pydub>=0.25.1
Requires-Dist: pykanto>=0.1.7
Requires-Dist: scikit-learn>=1.7.2
Requires-Dist: scipy>=1.16.3
Requires-Dist: setuptools<81
Requires-Dist: soxr>=1.0.0
Requires-Dist: tensorflow>=2.20.0
Requires-Dist: torch>=2.9.1
Requires-Dist: torchaudio>=2.9.1
Requires-Dist: tqdm>=4.67.1
Requires-Dist: transformers>=4.57.3
Provides-Extra: docs
Requires-Dist: sphinx>=5.0.0; extra == "docs"
Requires-Dist: sphinx-book-theme>=1.0.0; extra == "docs"
Requires-Dist: myst-parser>=2.0.0; extra == "docs"
Requires-Dist: nbsphinx>=0.9.0; extra == "docs"
Requires-Dist: sphinxcontrib-mermaid>=0.9.0; extra == "docs"
Dynamic: license-file
